riak_sessions
