Metadata-Version: 1.1
Name: dj-riak-sessions
Version: 0.3.0
Summary: Django session backend that stores sessions in a Riak database
Home-page: http://github.com/alesbublik/dj-riak-sessions
Author: Ales Bublik
Author-email: ales.bublik@gmail.com
License: BSD
Keywords: django,sessions,riak
Platform: UNKNOWN
Classifier: Programming Language :: Python :: 2
Classifier: Programming Language :: Python :: 3
Classifier: Topic :: Software Development :: Libraries :: Python Modules
Classifier: Framework :: Django
Classifier: Environment :: Web Environment
